{
  "projects": [
    {
      "id": "1",
      "ProjectName": "Website Redesign",
      "DueDate": "2025-09-30",
      "Description": "Revamp the company website for modern UI and better UX.",
      "Status": "In Progress",
      "PaymentMethod": "Credit Card",
      "CustomerName": "John Doe",
      "CustomerDetails": "john@example.com, +123456789"
    },
    {
      "id": "2",
      "ProjectName": "Mobile App Development",
      "DueDate": "2025-11-15",
      "Description": "Develop a cross-platform mobile app for our services.",
      "Status": "To Do",
      "PaymentMethod": "Bank Transfer",
      "CustomerName": "Acme Corp",
      "CustomerDetails": "contact@acme.com, +987654321"
    },
    {
      "id": "3",
      "ProjectName": "SEO Optimization",
      "DueDate": "2025-10-10",
      "Description": "Improve search engine rankings for target keywords.",
      "Status": "Completed",
      "PaymentMethod": "PayPal",
      "CustomerName": "Jane Smith",
      "CustomerDetails": "jane@domain.com, +192837465"
    }
  ]
}
